zoomdl/__init__.py
zoomdl/downloader.py
zoomdl/utils.py
zoomdl/version.py
zoom_downloader-1.0.0.dist-info/LICENSE
zoom_downloader-1.0.0.dist-info/METADATA
zoom_downloader-1.0.0.dist-info/WHEEL
zoom_downloader-1.0.0.dist-info/entry_points.txt
zoom_downloader-1.0.0.dist-info/top_level.txt
zoom_downloader-1.0.0.dist-info/RECORD
