Metadata-Version: 2.1
Name: zoom-downloader
Version: 1.0.0
Summary: Zoom recording downloader
Home-page: https://github.com/hykilpikonna/zoomdl
Author: Olivier Cloux & Azalea Gui
License: MIT
Platform: UNKNOWN
Classifier: License :: OSI Approved :: MIT License
Classifier: Programming Language :: Python :: 3
Classifier: Programming Language :: Python :: 3.7
Classifier: Programming Language :: Python :: 3.8
Classifier: Programming Language :: Python :: 3.9
Classifier: Programming Language :: Python :: 3.10
License-File: LICENSE
Requires-Dist: setuptools
Requires-Dist: typing-extensions
Requires-Dist: requests (~=2.28.1)
Requires-Dist: demjson3 (~=3.0.5)
Requires-Dist: tqdm (~=4.64.0)
